[{"review":"simple elegant exquisite sad good movies marketed reach masses people aware splendid movie exists slow pace movie kudos paresh rawal performing difficult role finesse splendid work amit rai taking small fundamental issue turning thought provoking masterpiece watch","label":0},{"review":"watch movie slightly flawed potrayal indian muslim hangs jinnahs picture house indian muslims love emotion hate extent good unity muslim community fight cats mosques rotten fish nice movie","label":0},{"review":"nice story sangam merging rivers ganga jamuna saraswati beautiful ending people religion walking unity differences","label":0},{"review":"positive movie omg dont people movie today","label":0},{"review":"recently movie ' important beautiful screenplay film absolutely fantastic","label":0},{"review":"movie indian cinema stupendous performance paresh rawal watch movie message reality","label":0},{"review":"learning movie ' ' made felt living era independence shows country powerful country time past invade britishers","label":0},{"review":"road sangam hidden gems indian cinema dont people watch movies concept shown movie universal","label":0},{"review":"great movie portrays muslim community befooled religion leaders","label":0},{"review":"boring movie acting good movies hindu muslim unity","label":0},{"review":"beautiful pure film india","label":0},{"review":"great movie watch indian hindu muslim sikh christian","label":0},{"review":"films director saab jug jug jio","label":0},{"review":"movie life","label":0},{"review":"' great movie ' watch","label":0},{"review":"absolutely watch movie marketed reach maximum audiences","label":0},{"review":"inspiring movie gandhiji india","label":0},{"review":"' nice movie kind sensitive movies advertised properly box office","label":0},{"review":"nice movie religious leaders community watch movie","label":0},{"review":"movie national integration","label":0},{"review":"good movie watch","label":0},{"review":"movie kind","label":0},{"review":"fantastic movie verygood acting actors","label":0},{"review":"inspiring simple movie watch","label":0},{"review":"awasome movie actors story","label":0}]