[{"review":"film film inspiring hope peoples connected film inspiration film yaa love share point view thax reading review","label":0},{"review":"favorite films story free spirited woman free spirited woman face choices act society believes woman zubeidaa live life choice matter led lovely character brings tears eyes watch movi","label":0},{"review":"understand didnt karisma national award award bigger national film award karisma' work movie sky touch reach awards sink front work","label":0},{"review":"loved movie specially song gae hain character played karishma worth loving decency touched heart","label":0},{"review":"zubeida killed husband madly love raja victor favorite movi","label":0},{"review":"song gaye hain heart touching song listen song automaticly tears eyes emotional music rahman sir","label":0},{"review":"beautifully crafted karishma kapoor' movie till date loved characters mandira devi","label":0},{"review":"zubeida character matches refused kings marriage proposal coz gave happiness world causing misery wip","label":0},{"review":"beautiful karishma movie awsm active watch movi","label":0},{"review":"beautiful emotional film characters watch","label":0},{"review":"loved movie ' simply shows emotional journey roles girl woman satisfied god dnt give emotional pain enemy 🙏","label":0},{"review":"excee excellent movie nice acting karishma","label":0},{"review":"nice movie गये है song fav","label":0},{"review":"finest film indian film industry watch","label":0},{"review":"movie loved actress karisma","label":0},{"review":"great movie underrated gem indian cinema","label":0},{"review":"song mehandi hai rachne wali good","label":0},{"review":"story incredibly awesom","label":0},{"review":"manoj bajpayee actor world","label":0},{"review":"movie times '","label":0},{"review":"awesome movi","label":0},{"review":"searching movi","label":0},{"review":"beautiful movie todays senseless movi","label":0}]